setup.py
compare_word/__init__.py
compare_word/compare_word.py
compare_word.egg-info/PKG-INFO
compare_word.egg-info/SOURCES.txt
compare_word.egg-info/dependency_links.txt
compare_word.egg-info/not-zip-safe
compare_word.egg-info/top_level.txt