Metadata-Version: 1.1
Name: compare-word
Version: 0.0.1
Summary: compare_word
Home-page: http://github.com/mvj3/compare_word/
Author: David Chen
Author-email: mvjome@gmail.com
License: MIT
Platform: any
Classifier: Intended Audience :: Developers
Classifier: Operating System :: OS Independent
Classifier: Programming Language :: Python
Classifier: Topic :: Software Development :: Libraries :: Python Modules
